[
  {
    "letter": "A",
    "file": "A.json",
    "count": 2528
  },
  {
    "letter": "B",
    "file": "B.json",
    "count": 4241
  },
  {
    "letter": "Ch",
    "file": "Ch.json",
    "count": 1698
  },
  {
    "letter": "D",
    "file": "D.json",
    "count": 2098
  },
  {
    "letter": "E",
    "file": "E.json",
    "count": 1082
  },
  {
    "letter": "F",
    "file": "F.json",
    "count": 791
  },
  {
    "letter": "G",
    "file": "G.json",
    "count": 1247
  },
  {
    "letter": "G'",
    "file": "G_.json",
    "count": 1009
  },
  {
    "letter": "H",
    "file": "H.json",
    "count": 1272
  },
  {
    "letter": "I",
    "file": "I.json",
    "count": 1686
  },
  {
    "letter": "J",
    "file": "J.json",
    "count": 1004
  },
  {
    "letter": "K",
    "file": "K.json",
    "count": 2952
  },
  {
    "letter": "L",
    "file": "L.json",
    "count": 695
  },
  {
    "letter": "M",
    "file": "M.json",
    "count": 2595
  },
  {
    "letter": "N",
    "file": "N.json",
    "count": 1163
  },
  {
    "letter": "O",
    "file": "O.json",
    "count": 1833
  },
  {
    "letter": "O'",
    "file": "O_.json",
    "count": 1054
  },
  {
    "letter": "P",
    "file": "P.json",
    "count": 2005
  },
  {
    "letter": "Q",
    "file": "Q.json",
    "count": 3404
  },
  {
    "letter": "R",
    "file": "R.json",
    "count": 1156
  },
  {
    "letter": "S",
    "file": "S.json",
    "count": 3795
  },
  {
    "letter": "Sh",
    "file": "Sh.json",
    "count": 1506
  },
  {
    "letter": "T",
    "file": "T.json",
    "count": 4566
  },
  {
    "letter": "U",
    "file": "U.json",
    "count": 1005
  },
  {
    "letter": "V",
    "file": "V.json",
    "count": 795
  },
  {
    "letter": "X",
    "file": "X.json",
    "count": 1167
  },
  {
    "letter": "Y",
    "file": "Y.json",
    "count": 2064
  },
  {
    "letter": "Z",
    "file": "Z.json",
    "count": 726
  }
]